autosignin/__init__.py
autosignin/test1.py
autosignup/__init__.py
autosignup/test1.py
signin/__init__.py
signin/test1.py
autosignup-0.0.2.dist-info/LICENSE.txt
autosignup-0.0.2.dist-info/METADATA
autosignup-0.0.2.dist-info/WHEEL
autosignup-0.0.2.dist-info/entry_points.txt
autosignup-0.0.2.dist-info/top_level.txt
autosignup-0.0.2.dist-info/RECORD
